autora/experiment_runner/synthetic/abstract/equation/__init__.py
autora_synthetic_abstract_equation-0.1.0.dist-info/METADATA
autora_synthetic_abstract_equation-0.1.0.dist-info/WHEEL
autora_synthetic_abstract_equation-0.1.0.dist-info/top_level.txt
autora_synthetic_abstract_equation-0.1.0.dist-info/RECORD
