Metadata-Version: 2.1
Name: autora-synthetic-abstract-equation
Version: 0.1.0
Summary: An experiment runner from arbitrary equations
Author-email: Younes Strittmatter <younes_strtittmatter@brown.edu>
License: MIT license
Project-URL: homepage, http://www.empiricalresearch.ai
Project-URL: repository, https://github.com/AutoResearch/autora-synthetic-abstract-equation
Project-URL: documentation, https://autoresearch.github.io/autora/
Requires-Python: <4,>=3.8
Requires-Dist: autora-core
Requires-Dist: autora-synthetic
Requires-Dist: scikit-learn
Requires-Dist: sympy
Provides-Extra: dev
Requires-Dist: autora-core[dev] ; extra == 'dev'
